{
  "dataset_name": "chestmnist",
  "adaptation_method": "frozen_feature_knn",
  "run_name": "rad_dino_518",
  "model_name": "microsoft/rad-dino",
  "image_size": 518,
  "data_fraction": 1.0,
  "dataset_seed": 0,
  "batch_size": 8,
  "knn_batch_size": 256,
  "thresholds": [
    0.01,
    0.03,
    0.05,
    0.1,
    0.15,
    0.2,
    0.3,
    0.5
  ],
  "selection_metric": "f1_macro_mean",
  "num_knn_settings": 73,
  "num_reference_set_groups": 12,
  "num_thresholds": 8,
  "num_total_metric_rows": 5048,
  "n_train": 78468,
  "n_val": 11219,
  "device": "cuda",
  "torch_version": "2.3.1+cu118",
  "transformers_version": "4.57.6",
  "total_params": 86580480,
  "trainable_params": 0,
  "trainable_param_fraction": 0.0,
  "feature_dim": 768,
  "feature_storage_mb": 262.7548828125,
  "train_feature_seconds": 3103.915782016935,
  "val_feature_seconds": 446.85665972414427,
  "feature_extraction_seconds": 3550.772441741079,
  "adaptation_seconds": 0.0,
  "inference_or_eval_seconds": 5.6350742757786065,
  "threshold_search_seconds": 528.1433857765514,
  "efficiency_counted_seconds": 4084.550901793409,
  "actual_wall_seconds": 4086.396745654056,
  "peak_gpu_memory_mb": 844.63525390625,
  "shortcut_used": false
}